pyhyypapi/__init__.py
pyhyypapi/__main__.py
pyhyypapi/alarm_info.py
pyhyypapi/android_checkin_pb2.py
pyhyypapi/checkin_pb2.py
pyhyypapi/client.py
pyhyypapi/constants.py
pyhyypapi/exceptions.py
pyhyypapi/mcs_pb2.py
pyhyypapi/push_receiver.py
pyhyypapi-0.0.0.8.dist-info/LICENSE.md
pyhyypapi-0.0.0.8.dist-info/METADATA
pyhyypapi-0.0.0.8.dist-info/WHEEL
pyhyypapi-0.0.0.8.dist-info/top_level.txt
pyhyypapi-0.0.0.8.dist-info/RECORD
