Metadata-Version: 2.1
Name: pyhyypapi
Version: 0.0.0.8
Summary: IDS Hyyp/ADT Secure Home API
Home-page: https://github.com/RenierM26/pyHyypApi/
Author: Renier Moorcroft
Author-email: renierm26@users.github.com
License: Apache Software License 2.0
Requires-Python: >=3.6
License-File: LICENSE.md
Requires-Dist: requests
Requires-Dist: pandas
Requires-Dist: oscrypto
Requires-Dist: protobuf
Requires-Dist: http-ece
Requires-Dist: appdirs
